[{"data": "https://airbnb-labelbox.s3.us-east-1.amazonaws.com/flex_dest_qa~cks9lwd2d041u0yal78dj3nz0~2021_09_08~1282_498a58d9/auto_gen_text_350_pool_acceptable_20210908_16..json", "externalId": "pool_acceptable_20210908_16"}, {"data": "https://airbnb-labelbox.s3.us-east-1.amazonaws.com/flex_dest_qa~cks9lwd2d041u0yal78dj3nz0~2021_09_08~1282_498a58d9/auto_gen_text_351_pool_acceptable_20210908_160..json", "externalId": "pool_acceptable_20210908_160"}, {"data": "https://airbnb-labelbox.s3.us-east-1.amazonaws.com/flex_dest_qa~cks9lwd2d041u0yal78dj3nz0~2021_09_08~1282_498a58d9/auto_gen_text_352_pool_acceptable_20210908_161..json", "externalId": "pool_acceptable_20210908_161"}, {"data": "https://airbnb-labelbox.s3.us-east-1.amazonaws.com/flex_dest_qa~cks9lwd2d041u0yal78dj3nz0~2021_09_08~1282_498a58d9/auto_gen_text_353_pool_acceptable_20210908_162..json", "externalId": "pool_acceptable_20210908_162"}, {"data": "https://airbnb-labelbox.s3.us-east-1.amazonaws.com/flex_dest_qa~cks9lwd2d041u0yal78dj3nz0~2021_09_08~1282_498a58d9/auto_gen_text_354_pool_acceptable_20210908_163..json", "externalId": "pool_acceptable_20210908_163"}, {"data": "https://airbnb-labelbox.s3.us-east-1.amazonaws.com/flex_dest_qa~cks9lwd2d041u0yal78dj3nz0~2021_09_08~1282_498a58d9/auto_gen_text_355_pool_acceptable_20210908_164..json", "externalId": "pool_acceptable_20210908_164"}, {"data": "https://airbnb-labelbox.s3.us-east-1.amazonaws.com/flex_dest_qa~cks9lwd2d041u0yal78dj3nz0~2021_09_08~1282_498a58d9/auto_gen_text_356_pool_acceptable_20210908_165..json", "externalId": "pool_acceptable_20210908_165"}, {"data": "https://airbnb-labelbox.s3.us-east-1.amazonaws.com/flex_dest_qa~cks9lwd2d041u0yal78dj3nz0~2021_09_08~1282_498a58d9/auto_gen_text_357_pool_acceptable_20210908_166..json", "externalId": "pool_acceptable_20210908_166"}, {"data": "https://airbnb-labelbox.s3.us-east-1.amazonaws.com/flex_dest_qa~cks9lwd2d041u0yal78dj3nz0~2021_09_08~1282_498a58d9/auto_gen_text_358_pool_acceptable_20210908_167..json", "externalId": "pool_acceptable_20210908_167"}, {"data": "https://airbnb-labelbox.s3.us-east-1.amazonaws.com/flex_dest_qa~cks9lwd2d041u0yal78dj3nz0~2021_09_08~1282_498a58d9/auto_gen_text_359_pool_acceptable_20210908_168..json", "externalId": "pool_acceptable_20210908_168"}, {"data": "https://airbnb-labelbox.s3.us-east-1.amazonaws.com/flex_dest_qa~cks9lwd2d041u0yal78dj3nz0~2021_09_08~1282_498a58d9/auto_gen_text_360_pool_acceptable_20210908_169..json", "externalId": "pool_acceptable_20210908_169"}, {"data": "https://airbnb-labelbox.s3.us-east-1.amazonaws.com/flex_dest_qa~cks9lwd2d041u0yal78dj3nz0~2021_09_08~1282_498a58d9/auto_gen_text_361_pool_acceptable_20210908_17..json", "externalId": "pool_acceptable_20210908_17"}, {"data": "https://airbnb-labelbox.s3.us-east-1.amazonaws.com/flex_dest_qa~cks9lwd2d041u0yal78dj3nz0~2021_09_08~1282_498a58d9/auto_gen_text_362_pool_acceptable_20210908_170..json", "externalId": "pool_acceptable_20210908_170"}, {"data": "https://airbnb-labelbox.s3.us-east-1.amazonaws.com/flex_dest_qa~cks9lwd2d041u0yal78dj3nz0~2021_09_08~1282_498a58d9/auto_gen_text_363_pool_acceptable_20210908_171..json", "externalId": "pool_acceptable_20210908_171"}, {"data": "https://airbnb-labelbox.s3.us-east-1.amazonaws.com/flex_dest_qa~cks9lwd2d041u0yal78dj3nz0~2021_09_08~1282_498a58d9/auto_gen_text_364_pool_acceptable_20210908_172..json", "externalId": "pool_acceptable_20210908_172"}, {"data": "https://airbnb-labelbox.s3.us-east-1.amazonaws.com/flex_dest_qa~cks9lwd2d041u0yal78dj3nz0~2021_09_08~1282_498a58d9/auto_gen_text_365_pool_acceptable_20210908_173..json", "externalId": "pool_acceptable_20210908_173"}, {"data": "https://airbnb-labelbox.s3.us-east-1.amazonaws.com/flex_dest_qa~cks9lwd2d041u0yal78dj3nz0~2021_09_08~1282_498a58d9/auto_gen_text_366_pool_acceptable_20210908_174..json", "externalId": "pool_acceptable_20210908_174"}, {"data": "https://airbnb-labelbox.s3.us-east-1.amazonaws.com/flex_dest_qa~cks9lwd2d041u0yal78dj3nz0~2021_09_08~1282_498a58d9/auto_gen_text_367_pool_acceptable_20210908_175..json", "externalId": "pool_acceptable_20210908_175"}, {"data": "https://airbnb-labelbox.s3.us-east-1.amazonaws.com/flex_dest_qa~cks9lwd2d041u0yal78dj3nz0~2021_09_08~1282_498a58d9/auto_gen_text_368_pool_acceptable_20210908_176..json", "externalId": "pool_acceptable_20210908_176"}, {"data": "https://airbnb-labelbox.s3.us-east-1.amazonaws.com/flex_dest_qa~cks9lwd2d041u0yal78dj3nz0~2021_09_08~1282_498a58d9/auto_gen_text_369_pool_acceptable_20210908_177..json", "externalId": "pool_acceptable_20210908_177"}, {"data": "https://airbnb-labelbox.s3.us-east-1.amazonaws.com/flex_dest_qa~cks9lwd2d041u0yal78dj3nz0~2021_09_08~1282_498a58d9/auto_gen_text_370_pool_acceptable_20210908_178..json", "externalId": "pool_acceptable_20210908_178"}, {"data": "https://airbnb-labelbox.s3.us-east-1.amazonaws.com/flex_dest_qa~cks9lwd2d041u0yal78dj3nz0~2021_09_08~1282_498a58d9/auto_gen_text_371_pool_acceptable_20210908_179..json", "externalId": "pool_acceptable_20210908_179"}, {"data": "https://airbnb-labelbox.s3.us-east-1.amazonaws.com/flex_dest_qa~cks9lwd2d041u0yal78dj3nz0~2021_09_08~1282_498a58d9/auto_gen_text_372_pool_acceptable_20210908_18..json", "externalId": "pool_acceptable_20210908_18"}, {"data": "https://airbnb-labelbox.s3.us-east-1.amazonaws.com/flex_dest_qa~cks9lwd2d041u0yal78dj3nz0~2021_09_08~1282_498a58d9/auto_gen_text_373_pool_acceptable_20210908_180..json", "externalId": "pool_acceptable_20210908_180"}, {"data": "https://airbnb-labelbox.s3.us-east-1.amazonaws.com/flex_dest_qa~cks9lwd2d041u0yal78dj3nz0~2021_09_08~1282_498a58d9/auto_gen_text_374_pool_acceptable_20210908_181..json", "externalId": "pool_acceptable_20210908_181"}, {"data": "https://airbnb-labelbox.s3.us-east-1.amazonaws.com/flex_dest_qa~cks9lwd2d041u0yal78dj3nz0~2021_09_08~1282_498a58d9/auto_gen_text_375_pool_acceptable_20210908_182..json", "externalId": "pool_acceptable_20210908_182"}, {"data": "https://airbnb-labelbox.s3.us-east-1.amazonaws.com/flex_dest_qa~cks9lwd2d041u0yal78dj3nz0~2021_09_08~1282_498a58d9/auto_gen_text_376_pool_acceptable_20210908_183..json", "externalId": "pool_acceptable_20210908_183"}, {"data": "https://airbnb-labelbox.s3.us-east-1.amazonaws.com/flex_dest_qa~cks9lwd2d041u0yal78dj3nz0~2021_09_08~1282_498a58d9/auto_gen_text_377_pool_acceptable_20210908_184..json", "externalId": "pool_acceptable_20210908_184"}, {"data": "https://airbnb-labelbox.s3.us-east-1.amazonaws.com/flex_dest_qa~cks9lwd2d041u0yal78dj3nz0~2021_09_08~1282_498a58d9/auto_gen_text_378_pool_acceptable_20210908_185..json", "externalId": "pool_acceptable_20210908_185"}, {"data": "https://airbnb-labelbox.s3.us-east-1.amazonaws.com/flex_dest_qa~cks9lwd2d041u0yal78dj3nz0~2021_09_08~1282_498a58d9/auto_gen_text_379_pool_acceptable_20210908_186..json", "externalId": "pool_acceptable_20210908_186"}, {"data": "https://airbnb-labelbox.s3.us-east-1.amazonaws.com/flex_dest_qa~cks9lwd2d041u0yal78dj3nz0~2021_09_08~1282_498a58d9/auto_gen_text_380_pool_acceptable_20210908_187..json", "externalId": "pool_acceptable_20210908_187"}, {"data": "https://airbnb-labelbox.s3.us-east-1.amazonaws.com/flex_dest_qa~cks9lwd2d041u0yal78dj3nz0~2021_09_08~1282_498a58d9/auto_gen_text_381_pool_acceptable_20210908_188..json", "externalId": "pool_acceptable_20210908_188"}, {"data": "https://airbnb-labelbox.s3.us-east-1.amazonaws.com/flex_dest_qa~cks9lwd2d041u0yal78dj3nz0~2021_09_08~1282_498a58d9/auto_gen_text_382_pool_acceptable_20210908_189..json", "externalId": "pool_acceptable_20210908_189"}, {"data": "https://airbnb-labelbox.s3.us-east-1.amazonaws.com/flex_dest_qa~cks9lwd2d041u0yal78dj3nz0~2021_09_08~1282_498a58d9/auto_gen_text_383_pool_acceptable_20210908_19..json", "externalId": "pool_acceptable_20210908_19"}, {"data": "https://airbnb-labelbox.s3.us-east-1.amazonaws.com/flex_dest_qa~cks9lwd2d041u0yal78dj3nz0~2021_09_08~1282_498a58d9/auto_gen_text_384_pool_acceptable_20210908_190..json", "externalId": "pool_acceptable_20210908_190"}, {"data": "https://airbnb-labelbox.s3.us-east-1.amazonaws.com/flex_dest_qa~cks9lwd2d041u0yal78dj3nz0~2021_09_08~1282_498a58d9/auto_gen_text_385_pool_acceptable_20210908_191..json", "externalId": "pool_acceptable_20210908_191"}, {"data": "https://airbnb-labelbox.s3.us-east-1.amazonaws.com/flex_dest_qa~cks9lwd2d041u0yal78dj3nz0~2021_09_08~1282_498a58d9/auto_gen_text_386_pool_acceptable_20210908_192..json", "externalId": "pool_acceptable_20210908_192"}, {"data": "https://airbnb-labelbox.s3.us-east-1.amazonaws.com/flex_dest_qa~cks9lwd2d041u0yal78dj3nz0~2021_09_08~1282_498a58d9/auto_gen_text_387_pool_acceptable_20210908_193..json", "externalId": "pool_acceptable_20210908_193"}, {"data": "https://airbnb-labelbox.s3.us-east-1.amazonaws.com/flex_dest_qa~cks9lwd2d041u0yal78dj3nz0~2021_09_08~1282_498a58d9/auto_gen_text_388_pool_acceptable_20210908_194..json", "externalId": "pool_acceptable_20210908_194"}, {"data": "https://airbnb-labelbox.s3.us-east-1.amazonaws.com/flex_dest_qa~cks9lwd2d041u0yal78dj3nz0~2021_09_08~1282_498a58d9/auto_gen_text_389_pool_acceptable_20210908_195..json", "externalId": "pool_acceptable_20210908_195"}, {"data": "https://airbnb-labelbox.s3.us-east-1.amazonaws.com/flex_dest_qa~cks9lwd2d041u0yal78dj3nz0~2021_09_08~1282_498a58d9/auto_gen_text_390_pool_acceptable_20210908_196..json", "externalId": "pool_acceptable_20210908_196"}, {"data": "https://airbnb-labelbox.s3.us-east-1.amazonaws.com/flex_dest_qa~cks9lwd2d041u0yal78dj3nz0~2021_09_08~1282_498a58d9/auto_gen_text_391_pool_acceptable_20210908_197..json", "externalId": "pool_acceptable_20210908_197"}, {"data": "https://airbnb-labelbox.s3.us-east-1.amazonaws.com/flex_dest_qa~cks9lwd2d041u0yal78dj3nz0~2021_09_08~1282_498a58d9/auto_gen_text_392_pool_acceptable_20210908_198..json", "externalId": "pool_acceptable_20210908_198"}, {"data": "https://airbnb-labelbox.s3.us-east-1.amazonaws.com/flex_dest_qa~cks9lwd2d041u0yal78dj3nz0~2021_09_08~1282_498a58d9/auto_gen_text_393_pool_acceptable_20210908_199..json", "externalId": "pool_acceptable_20210908_199"}, {"data": "https://airbnb-labelbox.s3.us-east-1.amazonaws.com/flex_dest_qa~cks9lwd2d041u0yal78dj3nz0~2021_09_08~1282_498a58d9/auto_gen_text_394_pool_acceptable_20210908_2..json", "externalId": "pool_acceptable_20210908_2"}, {"data": "https://airbnb-labelbox.s3.us-east-1.amazonaws.com/flex_dest_qa~cks9lwd2d041u0yal78dj3nz0~2021_09_08~1282_498a58d9/auto_gen_text_395_pool_acceptable_20210908_20..json", "externalId": "pool_acceptable_20210908_20"}, {"data": "https://airbnb-labelbox.s3.us-east-1.amazonaws.com/flex_dest_qa~cks9lwd2d041u0yal78dj3nz0~2021_09_08~1282_498a58d9/auto_gen_text_396_pool_acceptable_20210908_200..json", "externalId": "pool_acceptable_20210908_200"}, {"data": "https://airbnb-labelbox.s3.us-east-1.amazonaws.com/flex_dest_qa~cks9lwd2d041u0yal78dj3nz0~2021_09_08~1282_498a58d9/auto_gen_text_397_pool_acceptable_20210908_201..json", "externalId": "pool_acceptable_20210908_201"}, {"data": "https://airbnb-labelbox.s3.us-east-1.amazonaws.com/flex_dest_qa~cks9lwd2d041u0yal78dj3nz0~2021_09_08~1282_498a58d9/auto_gen_text_398_pool_acceptable_20210908_202..json", "externalId": "pool_acceptable_20210908_202"}, {"data": "https://airbnb-labelbox.s3.us-east-1.amazonaws.com/flex_dest_qa~cks9lwd2d041u0yal78dj3nz0~2021_09_08~1282_498a58d9/auto_gen_text_399_pool_acceptable_20210908_203..json", "externalId": "pool_acceptable_20210908_203"}]